RandAugment3d/__init__.py
RandAugment3d/augmentations.py
RandAugment3d-0.0.4.1.dev0.dist-info/LICENSE
RandAugment3d-0.0.4.1.dev0.dist-info/METADATA
RandAugment3d-0.0.4.1.dev0.dist-info/WHEEL
RandAugment3d-0.0.4.1.dev0.dist-info/top_level.txt
RandAugment3d-0.0.4.1.dev0.dist-info/RECORD
