Metadata-Version: 2.1
Name: RandAugment3d
Version: 0.0.4.1.dev0
Summary: Implementation of RandAugment in 3D
Home-page: https://github.com/JulianKlug/RandAugment-3D
Author: Julian Klug
Author-email: tensu.wave@gmail.com
License: GNUv3
Keywords: randaugment,data-augmentation,volume
Platform: UNKNOWN
Provides: RandAugment3d
Requires-Python: >=3.7
License-File: LICENSE
Requires-Dist: scikit-image
Requires-Dist: tensorflow
Requires-Dist: numpy
Requires-Dist: monai
Provides-Extra: docs
Requires-Dist: sphinx ; extra == 'docs'
Requires-Dist: sphinx-rtd-theme ; extra == 'docs'
Requires-Dist: sphinx-autodoc-typehints ; extra == 'docs'
Requires-Dist: sphinx-click ; extra == 'docs'
